multirex/__init__.py
multirex/__randinstrument.py
multirex/spectra.py
multirex/utils.py
multirex/version.py
multirex/data/__init__.py
multirex/data/opacCH4.dat
multirex/data/opacCO2.dat
multirex/data/opacH2O.dat
multirex/data/opacO2.dat
multirex/data/opacO3.dat
multirex/tests/__init__.py
multirex/tests/test_atmosphere.py
multirex/tests/test_atmosphere_extended.py
multirex/tests/test_parameter_exploration.py
multirex/tests/test_physics.py
multirex/tests/test_planet_atmosphere.py
multirex/tests/test_star.py
multirex/tests/test_summary.md
multirex/tests/test_system.py
multirex/tests/test_system_extended.py
multirex/tests/test_utils.py
multirex-0.3.2.dist-info/licenses/LICENSE
multirex-0.3.2.dist-info/METADATA
multirex-0.3.2.dist-info/WHEEL
multirex-0.3.2.dist-info/entry_points.txt
multirex-0.3.2.dist-info/top_level.txt
multirex-0.3.2.dist-info/RECORD
