Metadata-Version: 2.4
Name: multirex
Version: 0.3.2
Summary: Massive planetary spectra generator
Home-page: https://pypi.org/project/multirex
Author: David Duque-Castaño and Jorge I. Zuluaga
Author-email: dsantiago.duque@udea.edu.co
License: MIT
Keywords: exoplanets astrobiology astronomy spectroscopy
Classifier: Programming Language :: Python :: 3
Classifier: License :: OSI Approved :: MIT License
Classifier: Operating System :: OS Independent
License-File: LICENSE
Requires-Dist: numpy
Requires-Dist: taurex==3.1.14
Requires-Dist: matplotlib
Requires-Dist: tqdm
Requires-Dist: pandas
Requires-Dist: gdown
Requires-Dist: pyarrow
Requires-Dist: joblib
Requires-Dist: astropy
Dynamic: author
Dynamic: author-email
Dynamic: classifier
Dynamic: description
Dynamic: description-content-type
Dynamic: home-page
Dynamic: keywords
Dynamic: license
Dynamic: license-file
Dynamic: requires-dist
Dynamic: summary
